MANIFEST.in
README.md
setup.py
bin/grattify
grattify/__init__.py
grattify.egg-info/PKG-INFO
grattify.egg-info/SOURCES.txt
grattify.egg-info/dependency_links.txt
grattify.egg-info/requires.txt
grattify.egg-info/top_level.txt