Metadata-Version: 1.1
Name: grattify
Version: 0.2.9
Summary: Script to download music
Home-page: https://github.com/etaba/grattify
Author: Eric Taba
Author-email: eptaba@gmail.com
License: UNKNOWN
Download-URL: https://github.com/etaba/grattify/tarball/0.1
Keywords: music,spotify,pandora,download,song,youtube
Platform: UNKNOWN
